tree_sitter_luau/__init__.pyi
tree_sitter_luau/binding.c
tree_sitter_luau/__init__.py
tree_sitter_luau/py.typed
tree_sitter_luau/_binding.abi3.so
tree_sitter_luau/queries/locals.scm
tree_sitter_luau/queries/indents.scm
tree_sitter_luau/queries/highlights.scm
tree_sitter_luau/queries/folds.scm
tree_sitter_luau/queries/injections.scm
tree_sitter_luau-1.2.0.dist-info/RECORD
tree_sitter_luau-1.2.0.dist-info/LICENSE
tree_sitter_luau-1.2.0.dist-info/WHEEL
tree_sitter_luau-1.2.0.dist-info/top_level.txt
tree_sitter_luau-1.2.0.dist-info/METADATA
